json_db_lite/__init__.py
tests/__init__.py
tests/test_database.py
json_db_lite-0.1.2.dist-info/METADATA
json_db_lite-0.1.2.dist-info/WHEEL
json_db_lite-0.1.2.dist-info/top_level.txt
json_db_lite-0.1.2.dist-info/RECORD
