Metadata-Version: 2.1
Name: json-db-lite
Version: 0.1.2
Summary: A simple JSON file database manager
Home-page: https://github.com/Yakvenalex/json_database
Author: Alexey Yakovenko
Author-email: mr.mnogo@gmail.com
Classifier: Programming Language :: Python :: 3
Classifier: License :: OSI Approved :: MIT License
Classifier: Operating System :: OS Independent
Requires-Python: >=3.6
